{
    "name": "InkyPi Development",
    "display_type": "inky",
    "resolution": [
        800,
        480
    ],
    "orientation": "horizontal",
    "inverted_image": false,
    "image_settings": {
        "inky_saturation": 0.5
    },
    "plugin_order": [
        "meteoswiss_weather",
        "calendar",
        "ai_image",
        "ai_text",
        "clock",
        "comic",
        "countdown",
        "github",
        "image_album",
        "image_folder",
        "image_upload",
        "apod",
        "image_url",
        "newspaper",
        "rss",
        "screenshot",
        "todo_list",
        "unsplash",
        "weather",
        "wpotd",
        "year_progress"
    ],
    "playlist_config": {
        "playlists": [
            {
                "name": "Default",
                "start_time": "00:00",
                "end_time": "24:00",
                "plugins": [],
                "current_plugin_index": null
            }
        ],
        "active_playlist": null
    },
    "refresh_info": {
        "refresh_time": "2026-05-08T19:08:24.764919+00:00",
        "image_hash": "5c2aa3c689d50cf3f7a6f3b826cd40b6dcebc03e11474b2e9b88a3f7adab1d3e",
        "refresh_type": "Manual Update",
        "plugin_id": "meteoswiss_weather"
    }
}